Workbook

Sheet Data all
A1: DisNo. | B1: Disaster Subgroup | C1: Disaster Type | D1: Disaster Subtype | E1: Start Year | F1: Total Damage ('000 US$) | G1: External IDs | H1: ISO | I1: Country | J1: Location | K1: Origin | L1: Associated Types | M1: OFDA/BHA Response | N1: Appeal | O1: Declaration | P1: AID Contribution ('000 US$) | Q1: Magnitude | R1: Latitude | S1: Longitude | T1: River Basin
A2: 2000-0465-USA | B2: Climatological | C2: Wildfire | D2: Forest fire | E2: 2000 | F2: 1000000 | H2: USA | I2: United States of America | J2: Arizona, California, Colorado, Idaho, Montana, Nevada, New Mexico, Oregon, South Dakota, Texas, Utah, Washington, Wyoming, Florida, North Dakota provinces | M2: No | N2: No | O2: No | Q2: 680000
A3: 2000-0265-COL | B3: Hydrological | C3: Flood | D3: Riverine flood | E3: 2000 | H3: COL | I3: Colombia | J3: Narino, Putumayo, Santander, Antioquia, Choco, Cundinamarca, Tolima, Valle del Cauca, Amazonas provinces | K3: Heavy rains | L3: Slide (land, mud, snow, rock)|Transport accident | M3: No | N3: No | O3: No | P3: 9 | Q3: 200000 | T3: San Miguel
A4: 2000-0271-USA | B4: Hydrological | C4: Flood | D4: Flash flood | E4: 2000 | H4: USA | I4: United States of America | J4: Oklahoma province | K4: Brief torrential rain | M4: No | N4: No | O4: No | T4: Polecat Creek, Bird Creek, Neosho River, and Caney River
A5: 2000-0450-USA | B5: Climatological | C5: Wildfire | D5: Forest fire | E5: 2000 | H5: USA | I5: United States of America | J5: Alaska province | M5: No | N5: No | O5: No | Q5: 2363
A6: 2000-0466-BRA | B6: Hydrological | C6: Mass movement (wet) | D6: Mudslide | E6: 2000 | F6: 75000 | H6: BRA | I6: Brazil | J6: Alagoas, Pernambuco provinces | M6: No | N6: No | O6: No
A7: 2000-0502-USA | B7: Hydrological | C7: Flood | D7: Flood (General) | E7: 2000 | H7: USA | I7: United States of America | J7: Pennsylvania province | M7: No | N7: No | O7: No
A8: 2000-0853-ARG | B8: Climatological | C8: Wildfire | D8: Forest fire | E8: 2000 | H8: ARG | I8: Argentina | J8: La Pampa, Mendoza, San Luis, Formosa provinces | M8: No | N8: No | O8: No | Q8: 20500
A9: 2000-0865-USA | B9: Hydrological | C9: Flood | D9: Riverine flood | E9: 2000 | F9: 20000 | H9: USA | I9: United States of America | J9: Maui district (Hawaii province) | K9: Heavy rains | M9: No | N9: No | O9: No | Q9: 86
A10: 2000-0067-USA | B10: Meteorological | C10: Storm | D10: Tornado | E10: 2000 | H10: USA | I10: United States of America | J10: Bullock, Montgomery districts (Alabama province), Colquitt, Grady, Mitchell, Thomas, Tift districts (Georgia province), Washington district (Floride province), Lonoke, Prairie, Saline districts (Arkansas province) | M10: No | N10: No | O10: No | Q10: 249
A11: 2000-0098-COL | B11: Hydrological | C11: Flood | D11: Flood (General) | E11: 2000 | H11: COL | I11: Colombia | J11: Tolima, Santander, Valle provinces | M11: No | N11: No | O11: No
A12: 2000-0116-ARG | B12: Hydrological | C12: Flood | D12: Riverine flood | E12: 2000 | H12: ARG | I12: Argentina | J12: Catamarca, Cordoba, Jujuy, La Rioja, Santiago del Estero, Salta,Tucuman provinces | K12: Heavy rain | M12: No | N12: No | O12: No
A13: 2000-0204-ECU | B13: Biological | C13: Epidemic | D13: Parasitic disease | E13: 2000 | H13: ECU | I13: Ecuador | J13: Guayas, Los Rios provinces | M13: No | N13: No | O13: No
A14: 2000-0206-ECU | B14: Hydrological | C14: Mass movement (wet) | D14: Landslide (wet) | E14: 2000 | H14: ECU | I14: Ecuador | J14: Quito district (Pichincha province) | M14: No | N14: No | O14: No
A15: 2000-0130-BOL | B15: Hydrological | C15: Flood | D15: Riverine flood | E15: 2000 | H15: BOL | I15: Bolivia (Plurinational State of) | J15: Nuflo de Chavez, Obispo Santiesteban districts (Santa Cruz province), Bermejo town (Acre district, Tarija province), Avilez district (Tarija province), Gran Chaco district (Tarija province), Chuquisaca province | K15: Heavy rains | M15: No | N15: No | O15: No | Q15: 750 | T15: Bermejo, Grande
A16: 2000-0317-MEX | B16: Hydrological | C16: Flood | D16: Flood (General) | E16: 2000 | H16: MEX | I16: Mexico | J16: Chalco district (Mexico province) | M16: No | N16: No | O16: No
A17: 2000-0333-MEX | B17: Hydrological | C17: Flood | D17: Flood (General) | E17: 2000 | H17: MEX | I17: Mexico | J17: Acatlan de Perez Figueroa city (Tuxtepec district, Oaxaca province) | L17: Slide (land, mud, snow, rock) | M17: No | N17: No | O17: No
A18: 2000-0345-NIC | B18: Hydrological | C18: Flood | D18: Riverine flood | E18: 2000 | H18: NIC | I18: Nicaragua | J18: El Rama district (Atlantico Sur province) | M18: No | N18: No | O18: No
A19: 2000-0363-USA | B19: Climatological | C19: Wildfire | D19: Forest fire | E19: 2000 | H19: USA | I19: United States of America | J19: Park, Jefferson, Larimer districts (Colorado province) | M19: No | N19: No | O19: No | Q19: 85
A20: 2000-0586-PER | B20: Hydrological | C20: Mass movement (wet) | D20: Landslide (wet) | E20: 2000 | H20: PER | I20: Peru | J20: Arma village (La Convenci?n district, Cusco province) | M20: No | N20: No | O20: No
A21: 2000-0645-SLV | B21: Meteorological | C21: Storm | D21: Tropical cyclone | E21: 2000 | H21: SLV | I21: El Salvador | J21: Ahuachapan, Cabanas, Chalatenango, Cuscatlan, La Libertad, La Paz, La Union, Morazan, San Miguel, San Salvador, San Vicente, Santa Ana, Sonsonate, Usulutan provinces | M21: No | N21: No | O21: No
A22: 2000-0652-USA | B22: Meteorological | C22: Storm | D22: Tropical cyclone | E22: 2000 | F22: 219000 | H22: USA | I22: United States of America | J22: Miami-Dade, Monroe, Broward, Collier districts (Florida province) | M22: No | N22: No | O22: No
A23: 2000-0724-ECU | B23: Hydrological | C23: Mass movement (wet) | D23: Mudslide | E23: 2000 | H23: ECU | I23: Ecuador | J23: Penipe, Guano districts (Chimborazo province) | M23: No | N23: No | O23: No
A24: 2000-0839-ARG | B24: Meteorological | C24: Storm | D24: Lightning/Thunderstorms | E24: 2000 | H24: ARG | I24: Argentina | J24: Buenos Aires D.f., Buenos Aires provinces | M24: No | N24: No | O24: No | Q24: 96
A25: 2000-0827-MEX | B25: Meteorological | C25: Extreme temperature | D25: Cold wave | E25: 2000 | H25: MEX | I25: Mexico | J25: Chihuahua province | M25: No | N25: No | O25: No
A26: 2000-0905-BOL | B26: Hydrological | C26: Flood | D26: Flood (General) | E26: 2000 | H26: BOL | I26: Bolivia (Plurinational State of) | J26: Chuquisaca, Cochabamba, La Paz, Oruro, Potosi, Tarija provinces | L26: Slide (land, mud, snow, rock) | M26: No | N26: No | O26: No
A27: 2000-0919-USA | B27: Meteorological | C27: Storm | D27: Storm (General) | E27: 2000 | F27: 350000 | H27: USA | I27: United States of America | J27: Alabama, Georgia, Louisiana, North Carolina, South Carolina, Tennessee, Virginia, New York, Pennsylvania, Massachussetts provinces | L27: Cold wave | M27: No | N27: No | O27: No
A28: 2000-0937-USA | B28: Meteorological | C28: Storm | D28: Storm (General) | E28: 2000 | F28: 500000 | H28: USA | I28: United States of America | J28: Tuscaloosa district (Alabama province), Connecticut, Florida, Georgia, Massachusetts, Mississippi, Norh Carolina, New Jersey, New York, Pennsylvania, Rhode Island provinces | M28: No | N28: No | O28: No
A29: 2000-9339-USA | B29: Climatological | C29: Drought | D29: Drought | E29: 2000 | F29: 1100000 | H29: USA | I29: United States of America | J29: South Carolina, Georgia, Alabama, Florida, Louisiana, Texas provinces | M29: No | N29: No | O29: Yes
A30: 2000-9860-NIC | B30: Climatological | C30: Drought | D30: Drought | E30: 2000 | H30: NIC | I30: Nicaragua | J30: Atlantico Norte, Jinotega, Nueva Segovia provinces | L30: Famine | M30: No | N30: No | O30: No
A31: 2000-0128-USA | B31: Climatological | C31: Wildfire | D31: Forest fire | E31: 2000 | H31: USA | I31: United States of America | J31: Gainesville, Alachua areas (Alachua district, Florida province), Lafayette, Gulf districts (Florida province) | M31: No | N31: No | O31: No | Q31: 113
A32: 2000-0266-ECU | B32: Hydrological | C32: Flood | D32: Flood (General) | E32: 2000 | H32: ECU | I32: Ecuador | J32: Carchi, Imbabura provinces | M32: No | N32: No | O32: No
A33: 2000-0338-USA | B33: Meteorological | C33: Storm | D33: Tornado | E33: 2000 | F33: 28500 | H33: USA | I33: United States of America | J33: Adams, Columbia, Crawford, Dane, Dodge, Grant, Green, Iowa, Juneau, La crosse, Lafayette, Monroe, Richland, Rock, Sauk, Vernon districts (Wisconsin province) | M33: No | N33: No | O33: No
A34: 2000-0374-CRI | B34: Hydrological | C34: Mass movement (wet) | D34: Landslide (wet) | E34: 2000 | H34: CRI | I34: Costa Rica | J34: Miramar de Puntarenas town (Montes de Oro district, Puntarenas province) | M34: No | N34: No | O34: No
A35: 2000-0387-NIC | B35: Geophysical | C35: Earthquake | D35: Ground movement | E35: 2000 | G35: USGS:usp0009vy1 | H35: NIC | I35: Nicaragua | J35: Laguna de Apoyo nature reserve (Masaya district, Masaya province) | M35: No | N35: No | O35: No | P35: 69 | Q35: 5.4 | R35: 11.884 | S35: -85.988
A36: 2000-0406-USA | B36: Climatological | C36: Wildfire | D36: Forest fire | E36: 2000 | H36: USA | I36: United States of America | J36: Hanford area (Benton district, Washington province) | M36: No | N36: No | O36: No | Q36: 607
A37: 2000-0421-ARG | B37: Meteorological | C37: Extreme temperature | D37: Cold wave | E37: 2000 | H37: ARG | I37: Argentina | J37: Buenos Aires, Sante Fe, Formosa, Santa Cruz provinces | M37: No | N37: No | O37: No | Q37: 0
A38: 2000-0423-CHL | B38: Meteorological | C38: Extreme temperature | D38: Cold wave | E38: 2000 | F38: 10000 | H38: CHL | I38: Chile | J38: Antofagasta, Araucania, Arica y Painacota, Atacama, Coquimbo, Los Lagos, Los Rios, Tarapaca provinces | M38: No | N38: No | O38: No | Q38: -20
A39: 2000-0433-USA | B39: Meteorological | C39: Extreme temperature | D39: Heat wave | E39: 2000 | H39: USA | I39: United States of America | J39: Texas, Louisiana, Alabama provinces | M39: No | N39: No | O39: No | Q39: 38
A40: 2000-0595-SLV | B40: Hydrological | C40: Flood | D40: Riverine flood | E40: 2000 | H40: SLV | I40: El Salvador | J40: Cabanas, Cuscatlan, La Paz, La Union, Morazan, San Miguel, San Salvador, San Vicente, Usulutan provinces | K40: Heavy rain | M40: No | N40: No | O40: Yes
A41: 2000-0607-ARG | B41: Meteorological | C41: Storm | D41: Blizzard/Winter storm | E41: 2000 | H41: ARG | I41: Argentina | J41: Neugen, Rio Negro, Chubut, Santa Cruz (Patagonia region) | M41: No | N41: No | O41: No
A42: 2000-0642-BLZ | B42: Meteorological | C42: Storm | D42: Tropical cyclone | E42: 2000 | F42: 277460 | H42: BLZ | I42: Belize | J42: San Pedro and Belize cities, Cay Caulker and Ambergris Caye islands (Belize province), Corozal, Cayo, Orange Walk provinces | M42: Yes | N42: No | O42: No | P42: 2628 | Q42: 215
A43: 2000-0643-MEX | B43: Meteorological | C43: Storm | D43: Tropical cyclone | E43: 2000 | F43: 1000 | H43: MEX | I43: Mexico | J43: Puebla, Campeche, Quintana Roo, Yucatan, Veracruz, Chiapas, Oaxaca, Tabasco, Tamaulipas provinces | M43: No | N43: No | O43: No | Q43: 150
A44: 2000-0735-VEN | B44: Hydrological | C44: Flood | D44: Riverine flood | E44: 2000 | H44: VEN | I44: Venezuela (Bolivarian Republic of) | J44: Aragua, Carabobo, Falcon, Districto Capital, Merida, Miranda, Sucre, Trujillo, Vargas, Zulia provinces | K44: Heavy rain | M44: No | N44: No | O44: Yes | Q44: 77730
A45: 2000-0776-ARG | B45: Hydrological | C45: Flood | D45: Flood (General) | E45: 2000 | H45: ARG | I45: Argentina | J45: Canada de Gomez city (Iriondo disctrict, Santa Fe province) | M45: No | N45: No | O45: No
A46: 2000-0804-MEX | B46: Geophysical | C46: Volcanic activity | D46: Ash fall | E46: 2000 | H46: MEX | I46: Mexico | J46: Mexico, Puebla, Morelos provinces | M46: No | N46: No | O46: No | R46: 19.023 | S46: -98.622
A47: 2000-0838-USA | B47: Meteorological | C47: Storm | D47: Blizzard/Winter storm | E47: 2000 | H47: USA | I47: United States of America | J47: Texas, Oklahoma, New Mexico, Arkansas, Missouri, Minnesota provinces | L47: Transport accident | M47: No | N47: No | O47: No
A48: 2000-0875-NIC | B48: Meteorological | C48: Storm | D48: Tornado | E48: 2000 | H48: NIC | I48: Nicaragua | J48: El Viejo district (Chinandega province) | M48: No | N48: No | O48: No
A49: 2000-9496-CUB | B49: Climatological | C49: Drought | D49: Drought | E49: 2000 | H49: CUB | I49: Cuba | J49: Guantanamo, Santiago De Cuba, Las Tunas, Camaguey provinces | M49: No | N49: No | O49: Yes
A50: 2000-9712-USA | B50: Climatological | C50: Drought | D50: Drought | E50: 2000 | H50: USA | I50: United States of America | J50: Wyoming province | L50: Wildfire | M50: No | N50: No | O50: No
A51: 2000-0008-GTM | B51: Geophysical | C51: Volcanic activity | D51: Ash fall | E51: 2000 | H51: GTM | I51: Guatemala | J51: El Caracol, El Patrocinio, El Rodeo, San Francisco de Sales cities (San Vicente Pacaya district, Escuintla province) | M51: No | N51: No | O51: No | R51: 14.381 | S51: -90.601
A52: 2000-0019-BRA | B52: Hydrological | C52: Flood | D52: Riverine flood | E52: 2000 | H52: BRA | I52: Brazil | J52: Rio de Janeiro city (Rio de Janeiro district, Rio de Janeiro province), Sao Paulo city (Sao Paulo district, Sao Paulo province), Campos de Jordao city (Campos de Jordao district, Sao Paulo province). Volta Redonda district (Rio de Janeiro province), Barra Mansa district (Rio de Janeiro province), Resende district (Rio de Janeiro province), Pirangucu district (Minas Gerais province), Santa Rita do Sapucai district (Minas Gerais province). | K52: Heavy rains | L52: Slide (land, mud, snow, rock) | M52: No | N52: No | O52: Yes | Q52: 350000 | T52: Paraiba, Tiete, Maracana, Rio Verde
A53: 2000-0021-USA | B53: Meteorological | C53: Storm | D53: Tornado | E53: 2000 | F53: 210000 | H53: USA | I53: United States of America | J53: Crittenden, Daviess, Webster districts (Kentucky province) | M53: No | N53: No | O53: No
A54: 2000-0129-PER | B54: Hydrological | C54: Flood | D54: Flash flood | E54: 2000 | H54: PER | I54: Peru | J54: Hipre village (Uraya area, Angaraes district, Huancavelica province) | K54: Torrential rain | L54: Slide (land, mud, snow, rock) | M54: No | N54: No | O54: No
A55: 2000-0205-ECU | B55: Biological | C55: Epidemic | D55: Viral disease | E55: 2000 | H55: ECU | I55: Ecuador | M55: No | N55: No | O55: No
A56: 2000-0216-GUF | B56: Hydrological | C56: Mass movement (wet) | D56: Landslide (wet) | E56: 2000 | H56: GUF | I56: French Guiana | J56: Remire (Montjoly) district (Cayenne province) | K56: Heavy rains | M56: No | N56: No | O56: No
A57: 2000-0232-USA | B57: Hydrological | C57: Flood | D57: Flash flood | E57: 2000 | H57: USA | I57: United States of America | J57: Franklin, Jefferson districts (Missouri province) | K57: Brief torrential rain | M57: No | N57: No | O57: No | T57: Flat Creek, Bourbeuse, Big and Meramec rivers
A58: 2000-0275-URY | B58: Hydrological | C58: Flood | D58: Flood (General) | E58: 2000 | H58: URY | I58: Uruguay | J58: Artigas, Canelones, Cerro Largo, Colonia, Durazno, Flores, Florida, Lavalleja, Maldonado, Montevideo, Paysandu, Rio Negro, Rivera, Rocha, Salto, San Jose, Soriano, Tacuarembo, Treinta Y Tres provinces | M58: No | N58: No | O58: No
A59: 2000-0279-USA | B59: Climatological | C59: Wildfire | D59: Forest fire | E59: 2000 | H59: USA | I59: United States of America | J59: Sarasota district (Florida province) | M59: No | N59: No | O59: No | Q59: 16
A60: 2000-0296-USA | B60: Hydrological | C60: Flood | D60: Flood (General) | E60: 2000 | H60: USA | I60: United States of America | J60: Liberty district (Texas province) | M60: No | N60: No | O60: No
A61: 2000-0310-CHL | B61: Hydrological | C61: Flood | D61: Riverine flood | E61: 2000 | H61: CHL | I61: Chile | J61: Valdivia district (Los Rios province), Cautin district (Araucania province) | K61: Heavy rain | M61: No | N61: No | O61: No | Q61: 84000
A62: 2000-0360-USA | B62: Meteorological | C62: Storm | D62: Severe weather | E62: 2000 | H62: USA | I62: United States of America | J62: Anderson, Benton, Cheatham, Davidson, Henry, Hickman, Houston, Jackson, Knox, Lake, Obion, Perry, Pickett, Stewart districts (Tennessee province) | M62: No | N62: No | O62: No
A63: 2000-0422-URY | B63: Meteorological | C63: Extreme temperature | D63: Cold wave | E63: 2000 | H63: URY | I63: Uruguay | J63: Paysandu, Maldonado provinces | M63: No | N63: No | O63: No | Q63: -7.5
A64: 2000-0375-CHL | B64: Hydrological | C64: Flood | D64: Flash flood | E64: 2000 | F64: 30000 | H64: CHL | I64: Chile | J64: Metropolitana, Coquimbo, Valparaiso, Maule, Araucania, Los Lagos, Los Rios, Libertador Gral. Bernardo O'higgins provinces | L64: Rain | M64: Yes | N64: No | O64: No | P64: 1175
A65: 2000-0416-BOL | B65: Meteorological | C65: Extreme temperature | D65: Cold wave | E65: 2000 | H65: BOL | I65: Bolivia (Plurinational State of) | J65: Cochabamba, Santa Cruz, La Paz provinces | M65: No | N65: No | O65: No | Q65: -9
A66: 2000-0420-CAN | B66: Meteorological | C66: Storm | D66: Tornado | E66: 2000 | F66: 13000 | H66: CAN | I66: Canada | J66: Pine Lake area (Division No. 8 district, Alberta province) | M66: No | N66: No | O66: No | Q66: 300
A67: 2000-0463-USA | B67: Meteorological | C67: Storm | D67: Tornado | E67: 2000 | F67: 8100 | H67: USA | I67: United States of America | J67: Granite Falls city (Yellow Medicine, Minnesota province) | M67: No | N67: No | O67: No
A68: 2000-0500-USA | B68: Hydrological | C68: Flood | D68: Riverine flood | E68: 2000 | F68: 166000 | H68: USA | I68: United States of America | J68: Morris, Sussex districts (New Jersey province) | K68: Heavy rain | L68: Slide (land, mud, snow, rock) | M68: No | N68: No | O68: No
A69: 2000-0590-BRA | B69: Hydrological | C69: Flood | D69: Riverine flood | E69: 2000 | H69: BRA | I69: Brazil | J69: Recife city (Recife district, Pernambuco province), Jaboatao Dos Guararapes, Moreno districts (Pernambuco province) | K69: Heavy rain | M69: No | N69: No | O69: No | Q69: 3000
A70: 2000-0598-USA | B70: Geophysical | C70: Earthquake | D70: Ground movement | E70: 2000 | F70: 50000 | G70: USGS:usp0009zmm | H70: USA | I70: United States of America | J70: Near Yountville city (Napa district, California province) | M70: No | N70: No | O70: No | Q70: 4.9 | R70: 38.378833 | S70: -122.41333
A71: 2000-0611-MEX | B71: Meteorological | C71: Storm | D71: Severe weather | E71: 2000 | H71: MEX | I71: Mexico | J71: Chiapas, Veracruz, Guerrero provinces | M71: No | N71: No | O71: No | Q71: 88
A72: 2000-0614-USA | B72: Meteorological | C72: Storm | D72: Tornado | E72: 2000 | F72: 90000 | H72: USA | I72: United States of America | J72: Xenia city (Greene district, Ohio province) | M72: No | N72: No | O72: No
A73: 2000-0756-USA | B73: Meteorological | C73: Storm | D73: Blizzard/Winter storm | E73: 2000 | H73: USA | I73: United States of America | J73: Buffalo city (Erie district, New York province) | M73: No | N73: No | O73: No
A74: 2000-0797-HTI | B74: Hydrological | C74: Flood | D74: Flood (General) | E74: 2000 | H74: HTI | I74: Haiti | J74: Abricots village (Jeremie district, Grande Anse province) | M74: No | N74: No | O74: No
A75: 2000-0882-SLV | B75: Biological | C75: Epidemic | D75: Viral disease | E75: 2000 | H75: SLV | I75: El Salvador | M75: Yes | N75: No | O75: No
A76: 2000-9138-JAM | B76: Climatological | C76: Drought | D76: Drought | E76: 2000 | F76: 6000 | H76: JAM | I76: Jamaica | J76: Clarendon, Hanover, Manchester, Portland, Saint Ann, Saint Catherine, Saint Elizabeth, Saint James, Saint Thomas, Trelawny, Westmoreland provinces | M76: No | N76: No | O76: No
A77: 2000-9860-HND | B77: Climatological | C77: Drought | D77: Drought | E77: 2000 | H77: HND | I77: Honduras | J77: Montana de la Flor area (Marale district, Francisco Morazan province) | L77: Famine | M77: No | N77: No | O77: No
A78: 2000-0080-USA | B78: Hydrological | C78: Flood | D78: Riverine flood | E78: 2000 | H78: USA | I78: United States of America | J78: Kentucky, Ohio provinces | K78: Heavy rain | L78: Slide (land, mud, snow, rock) | M78: No | N78: No | O78: No | Q78: 55000 | T78: Licking River, Ohio River, Scioto River
A79: 2000-0081-COL | B79: Geophysical | C79: Earthquake | D79: Ground movement | E79: 2000 | G79: USGS:usp000a373 | H79: COL | I79: Colombia | J79: Jurado island and Jurado districts (Choco province) | M79: No | N79: No | O79: No | Q79: 6.5 | R79: 7.042 | S79: -77.829
A80: 2000-0175-USA | B80: Meteorological | C80: Storm | D80: Tornado | E80: 2000 | F80: 450000 | H80: USA | I80: United States of America | J80: Fort Worth Texas city (Tarrant district, Texas province), Reagan, Burleson districts (Texas province) | M80: No | N80: No | O80: No
A81: 2000-0215-HND | B81: Climatological | C81: Wildfire | D81: Forest fire | E81: 2000 | H81: HND | I81: Honduras | J81: Atlantida, Choluteca, Colon, Comayagua, Copan, Cortes, Francisco Morazan, Gracias A Dios, Intibuca, Islas De Bahia, La Paz, Lempira, Name Unknown, Ocotepeque, Olancho, Paraiso, Santa Barbara, Valle, Yoro provinces | M81: No | N81: No | O81: No | Q81: 125
A82: 2000-0240-USA | B82: Climatological | C82: Wildfire | D82: Forest fire | E82: 2000 | F82: 1500000 | H82: USA | I82: United States of America | J82: Los Alamos, Rio Arriba, Sandoval, Santa Fe districts (New Mexico province) | M82: No | N82: No | O82: No | Q82: 194
A83: 2000-0255-ARG | B83: Hydrological | C83: Flood | D83: Flood (General) | E83: 2000 | H83: ARG | I83: Argentina | J83: Avellaneda, Berisso, Lanus, Quilmes, San Fernando, San Miguel districts (Buenos Aires province), Rosario district (Santa Fe province), Parana city (Entre Rios province); Buenos Aires city (Buenos Aires D.f. province), La Pampa, La Cordoba provinces | M83: No | N83: No | O83: No
A84: 2000-0276-MEX | B84: Hydrological | C84: Flood | D84: Flash flood | E84: 2000 | H84: MEX | I84: Mexico | J84: Distrito Federal, Veracruz, Chiapas, Tabasco, Zacatecas provinces | M84: No | N84: No | O84: No
A85: 2000-0297-USA | B85: Hydrological | C85: Flood | D85: Flood (General) | E85: 2000 | F85: 100000 | H85: USA | I85: United States of America | J85: Franklin, Jefferson, Gasconade districts (Missouri province) | M85: No | N85: No | O85: No
A86: 2000-0299-GTM | B86: Hydrological | C86: Flood | D86: Riverine flood | E86: 2000 | H86: GTM | I86: Guatemala | J86: Guatemala district (Guatemala province), Alta Verapaz, Escuintla, Huehuetenango, Jalapa, Quiché, Totonicapan, Zacapa provinces | K86: Heavy rain | M86: No | N86: No | O86: Yes | Q86: 11600 | T86: Motagua river
A87: 2000-0403-PER | B87: Biological | C87: Infestation | D87: Locust infestation | E87: 2000 | H87: PER | I87: Peru | J87: Cajamarca, Lambayeque | M87: No | N87: No | O87: No
A88: 2000-0486-PRY | B88: Meteorological | C88: Extreme temperature | D88: Cold wave | E88: 2000 | H88: PRY | I88: Paraguay | J88: Alto Paraguay, Alto Parana, Amambay, Boqueron, Caaguazu, Caazapa, Canindeyu, Central, Concepcion, Cordillera, Guaira, Itapua, Misiones, Neembucu, Paraguari, Presidente Hayes, San Pedro provinces | M88: No | N88: No | O88: No | Q88: -5
A89: 2000-0609-GTM | B89: Hydrological | C89: Flood | D89: Riverine flood | E89: 2000 | H89: GTM | I89: Guatemala | J89: Teleman area (Panzos district, Alta Verapaz province), Guatemala district (Guatemala province), Zacapa district (Zacapa province) | K89: Heavy rain | L89: Slide (land, mud, snow, rock) | M89: No | N89: No | O89: No | Q89: 13970 | T89: Concepcion river
A90: 2000-0650-VEN | B90: Hydrological | C90: Flood | D90: Flood (General) | E90: 2000 | H90: VEN | I90: Venezuela (Bolivarian Republic of) | J90: Distrito Capital province | M90: No | N90: No | O90: No
A91: 2000-0627-PAN | B91: Hydrological | C91: Flood | D91: Flood (General) | E91: 2000 | F91: 1300 | H91: PAN | I91: Panama | J91: Chiriqui province | M91: No | N91: No | O91: No
A92: 2000-0644-NIC | B92: Meteorological | C92: Storm | D92: Tropical cyclone | E92: 2000 | F92: 1000 | H92: NIC | I92: Nicaragua | J92: Léon, Chinandega, Managua, Granada, Rivas provinces | M92: No | N92: No | O92: No
A93: 2000-0648-COL | B93: Hydrological | C93: Flood | D93: Riverine flood | E93: 2000 | H93: COL | I93: Colombia | J93: Ayapel district (Cordoba province), San Benito Abad district (Sucre province) | K93: Heavy rains | M93: No | N93: No | O93: No | T93: Magdalena, Cauca, San Jorge and Sinu
A94: 2000-0666-BRA | B94: Hydrological | C94: Flood | D94: Riverine flood | E94: 2000 | H94: BRA | I94: Brazil | J94: Rio Grande Do Sul province | K94: Heavy rain | M94: No | N94: No | O94: No | Q94: 10250
A95: 2000-0733-ARG | B95: Hydrological | C95: Flood | D95: Flood (General) | E95: 2000 | F95: 300000 | H95: ARG | I95: Argentina | J95: Buenos Aires, Cordoba, LaPampa, Santa Fe provinces | M95: No | N95: No | O95: No
A96: 2000-0809-BRA | B96: Hydrological | C96: Flood | D96: Riverine flood | E96: 2000 | H96: BRA | I96: Brazil | J96: Belo Horizonte district (Minas Gerais province), Santos, Guaruja districts (Sao Paulo province), Santa Leopoldina district (Espirito Santo province), Alto Feliz district (Rio Grande do Sul province) | K96: Heavy rains | L96: Slide (land, mud, snow, rock) | M96: No | N96: No | O96: No | Q96: 578300
A97: 2000-0840-URY | B97: Meteorological | C97: Storm | D97: Storm (General) | E97: 2000 | H97: URY | I97: Uruguay | J97: Canelones province | M97: No | N97: No | O97: No | Q97: 96
A98: 2000-0869-CUB | B98: Hydrological | C98: Flood | D98: Flood (General) | E98: 2000 | H98: CUB | I98: Cuba | J98: Centro Habana district (Ciudad de La Habana province) | M98: No | N98: No | O98: No
A99: 2000-9881-BOL | B99: Climatological | C99: Drought | D99: Drought | E99: 2000 | H99: BOL | I99: Bolivia (Plurinational State of) | J99: Gran Chaco district (Tarija province) | M99: Yes | N99: No | O99: No
A100: 2001-0553-BLZ | B100: Meteorological | C100: Storm | D100: Tropical cyclone | E100: 2001 | F100: 250000 | H100: BLZ | I100: Belize | J100: Toledo, Stann Creek provinces | M100: No | N100: No | O100: No | Q100: 233
...

Sheet EM-DAT Data
A1: DisNo. | B1: Disaster Subgroup | C1: Disaster Subtype | D1: Start Year | E1: Total Damage ('000 US$) | F1: Country | G1: Associated Types | H1: OFDA/BHA Response | I1: Appeal | J1: Declaration | K1: Total Affected | L1: Total Damage, Adjusted ('000 US$) | M1: CPI
A2: 2000-0465-USA | B2: Climatological | C2: Forest fire | D2: 2000 | E2: 1000000 | F2: United States of America | H2: No | I2: No | J2: No | K2: 1000 | L2: 1869587 | M2: 53.487737
A3: 2000-0265-COL | B3: Hydrological | C3: Riverine flood | D3: 2000 | F3: Colombia | G3: Slide (land, mud, snow, rock)|Transport accident | H3: No | I3: No | J3: No | K3: 12000 | M3: 53.487737
A4: 2000-0271-USA | B4: Hydrological | C4: Flash flood | D4: 2000 | F4: United States of America | H4: No | I4: No | J4: No | K4: 300 | M4: 53.487737
A5: 2000-0450-USA | B5: Climatological | C5: Forest fire | D5: 2000 | F5: United States of America | H5: No | I5: No | J5: No | M5: 53.487737
A6: 2000-0466-BRA | B6: Hydrological | C6: Mudslide | D6: 2000 | E6: 75000 | F6: Brazil | H6: No | I6: No | J6: No | K6: 143000 | L6: 140219 | M6: 53.487737
A7: 2000-0502-USA | B7: Hydrological | C7: Flood (General) | D7: 2000 | F7: United States of America | H7: No | I7: No | J7: No | K7: 300 | M7: 53.487737
A8: 2000-0853-ARG | B8: Climatological | C8: Forest fire | D8: 2000 | F8: Argentina | H8: No | I8: No | J8: No | M8: 53.487737
A9: 2000-0865-USA | B9: Hydrological | C9: Riverine flood | D9: 2000 | E9: 20000 | F9: United States of America | H9: No | I9: No | J9: No | K9: 100 | L9: 37392 | M9: 53.487737
A10: 2000-0067-USA | B10: Meteorological | C10: Tornado | D10: 2000 | F10: United States of America | H10: No | I10: No | J10: No | K10: 1000 | M10: 53.487737
A11: 2000-0098-COL | B11: Hydrological | C11: Flood (General) | D11: 2000 | F11: Colombia | H11: No | I11: No | J11: No | K11: 39000 | M11: 53.487737
A12: 2000-0116-ARG | B12: Hydrological | C12: Riverine flood | D12: 2000 | F12: Argentina | H12: No | I12: No | J12: No | K12: 6000 | M12: 53.487737
A13: 2000-0204-ECU | B13: Biological | C13: Parasitic disease | D13: 2000 | F13: Ecuador | H13: No | I13: No | J13: No | K13: 100000 | M13: 53.487737
A14: 2000-0206-ECU | B14: Hydrological | C14: Landslide (wet) | D14: 2000 | F14: Ecuador | H14: No | I14: No | J14: No | K14: 205 | M14: 53.487737
A15: 2000-0130-BOL | B15: Hydrological | C15: Riverine flood | D15: 2000 | F15: Bolivia (Plurinational State of) | H15: No | I15: No | J15: No | K15: 7000 | M15: 53.487737
A16: 2000-0317-MEX | B16: Hydrological | C16: Flood (General) | D16: 2000 | F16: Mexico | H16: No | I16: No | J16: No | K16: 2000 | M16: 53.487737
A17: 2000-0333-MEX | B17: Hydrological | C17: Flood (General) | D17: 2000 | F17: Mexico | G17: Slide (land, mud, snow, rock) | H17: No | I17: No | J17: No | M17: 53.487737
A18: 2000-0345-NIC | B18: Hydrological | C18: Riverine flood | D18: 2000 | F18: Nicaragua | H18: No | I18: No | J18: No | K18: 5500 | M18: 53.487737
A19: 2000-0363-USA | B19: Climatological | C19: Forest fire | D19: 2000 | F19: United States of America | H19: No | I19: No | J19: No | K19: 1010 | M19: 53.487737
A20: 2000-0586-PER | B20: Hydrological | C20: Landslide (wet) | D20: 2000 | F20: Peru | H20: No | I20: No | J20: No | M20: 53.487737
A21: 2000-0645-SLV | B21: Meteorological | C21: Tropical cyclone | D21: 2000 | F21: El Salvador | H21: No | I21: No | J21: No | K21: 100 | M21: 53.487737
A22: 2000-0652-USA | B22: Meteorological | C22: Tropical cyclone | D22: 2000 | E22: 219000 | F22: United States of America | H22: No | I22: No | J22: No | K22: 17433 | L22: 409440 | M22: 53.487737
A23: 2000-0724-ECU | B23: Hydrological | C23: Mudslide | D23: 2000 | F23: Ecuador | H23: No | I23: No | J23: No | K23: 180 | M23: 53.487737
A24: 2000-0839-ARG | B24: Meteorological | C24: Lightning/Thunderstorms | D24: 2000 | F24: Argentina | H24: No | I24: No | J24: No | K24: 430 | M24: 53.487737
A25: 2000-0827-MEX | B25: Meteorological | C25: Cold wave | D25: 2000 | F25: Mexico | H25: No | I25: No | J25: No | M25: 53.487737
A26: 2000-0905-BOL | B26: Hydrological | C26: Flood (General) | D26: 2000 | F26: Bolivia (Plurinational State of) | G26: Slide (land, mud, snow, rock) | H26: No | I26: No | J26: No | K26: 10 | M26: 53.487737
A27: 2000-0919-USA | B27: Meteorological | C27: Storm (General) | D27: 2000 | E27: 350000 | F27: United States of America | G27: Cold wave | H27: No | I27: No | J27: No | L27: 654356 | M27: 53.487737
A28: 2000-0937-USA | B28: Meteorological | C28: Storm (General) | D28: 2000 | E28: 500000 | F28: United States of America | H28: No | I28: No | J28: No | K28: 75 | L28: 934794 | M28: 53.487737
A29: 2000-9339-USA | B29: Climatological | C29: Drought | D29: 2000 | E29: 1100000 | F29: United States of America | H29: No | I29: No | J29: Yes | L29: 2056546 | M29: 53.487737
A30: 2000-9860-NIC | B30: Climatological | C30: Drought | D30: 2000 | F30: Nicaragua | G30: Famine | H30: No | I30: No | J30: No | M30: 53.487737
A31: 2000-0128-USA | B31: Climatological | C31: Forest fire | D31: 2000 | F31: United States of America | H31: No | I31: No | J31: No | K31: 600 | M31: 53.487737
A32: 2000-0266-ECU | B32: Hydrological | C32: Flood (General) | D32: 2000 | F32: Ecuador | H32: No | I32: No | J32: No | K32: 32 | M32: 53.487737
A33: 2000-0338-USA | B33: Meteorological | C33: Tornado | D33: 2000 | E33: 28500 | F33: United States of America | H33: No | I33: No | J33: No | L33: 53283 | M33: 53.487737
A34: 2000-0374-CRI | B34: Hydrological | C34: Landslide (wet) | D34: 2000 | F34: Costa Rica | H34: No | I34: No | J34: No | K34: 200 | M34: 53.487737
A35: 2000-0387-NIC | B35: Geophysical | C35: Ground movement | D35: 2000 | F35: Nicaragua | H35: No | I35: No | J35: No | K35: 7477 | M35: 53.487737
A36: 2000-0406-USA | B36: Climatological | C36: Forest fire | D36: 2000 | F36: United States of America | H36: No | I36: No | J36: No | K36: 8077 | M36: 53.487737
A37: 2000-0421-ARG | B37: Meteorological | C37: Cold wave | D37: 2000 | F37: Argentina | H37: No | I37: No | J37: No | K37: 300 | M37: 53.487737
A38: 2000-0423-CHL | B38: Meteorological | C38: Cold wave | D38: 2000 | E38: 10000 | F38: Chile | H38: No | I38: No | J38: No | L38: 18696 | M38: 53.487737
A39: 2000-0433-USA | B39: Meteorological | C39: Heat wave | D39: 2000 | F39: United States of America | H39: No | I39: No | J39: No | M39: 53.487737
A40: 2000-0595-SLV | B40: Hydrological | C40: Riverine flood | D40: 2000 | F40: El Salvador | H40: No | I40: No | J40: Yes | K40: 400 | M40: 53.487737
A41: 2000-0607-ARG | B41: Meteorological | C41: Blizzard/Winter storm | D41: 2000 | F41: Argentina | H41: No | I41: No | J41: No | M41: 53.487737
A42: 2000-0642-BLZ | B42: Meteorological | C42: Tropical cyclone | D42: 2000 | E42: 277460 | F42: Belize | H42: Yes | I42: No | J42: No | K42: 62570 | L42: 518736 | M42: 53.487737
A43: 2000-0643-MEX | B43: Meteorological | C43: Tropical cyclone | D43: 2000 | E43: 1000 | F43: Mexico | H43: No | I43: No | J43: No | K43: 30000 | L43: 1870 | M43: 53.487737
A44: 2000-0735-VEN | B44: Hydrological | C44: Riverine flood | D44: 2000 | F44: Venezuela (Bolivarian Republic of) | H44: No | I44: No | J44: Yes | K44: 7000 | M44: 53.487737
A45: 2000-0776-ARG | B45: Hydrological | C45: Flood (General) | D45: 2000 | F45: Argentina | H45: No | I45: No | J45: No | K45: 1800 | M45: 53.487737
A46: 2000-0804-MEX | B46: Geophysical | C46: Ash fall | D46: 2000 | F46: Mexico | H46: No | I46: No | J46: No | K46: 41000 | M46: 53.487737
A47: 2000-0838-USA | B47: Meteorological | C47: Blizzard/Winter storm | D47: 2000 | F47: United States of America | G47: Transport accident | H47: No | I47: No | J47: No | K47: 34 | M47: 53.487737
A48: 2000-0875-NIC | B48: Meteorological | C48: Tornado | D48: 2000 | F48: Nicaragua | H48: No | I48: No | J48: No | K48: 210 | M48: 53.487737
A49: 2000-9496-CUB | B49: Climatological | C49: Drought | D49: 2000 | F49: Cuba | H49: No | I49: No | J49: Yes | M49: 53.487737
A50: 2000-9712-USA | B50: Climatological | C50: Drought | D50: 2000 | F50: United States of America | G50: Wildfire | H50: No | I50: No | J50: No | M50: 53.487737
A51: 2000-0008-GTM | B51: Geophysical | C51: Ash fall | D51: 2000 | F51: Guatemala | H51: No | I51: No | J51: No | K51: 800 | M51: 53.487737
A52: 2000-0019-BRA | B52: Hydrological | C52: Riverine flood | D52: 2000 | F52: Brazil | G52: Slide (land, mud, snow, rock) | H52: No | I52: No | J52: Yes | K52: 70000 | M52: 53.487737
A53: 2000-0021-USA | B53: Meteorological | C53: Tornado | D53: 2000 | E53: 210000 | F53: United States of America | H53: No | I53: No | J53: No | K53: 162 | L53: 392613 | M53: 53.487737
A54: 2000-0129-PER | B54: Hydrological | C54: Flash flood | D54: 2000 | F54: Peru | G54: Slide (land, mud, snow, rock) | H54: No | I54: No | J54: No | K54: 50 | M54: 53.487737
A55: 2000-0205-ECU | B55: Biological | C55: Viral disease | D55: 2000 | F55: Ecuador | H55: No | I55: No | J55: No | K55: 220 | M55: 53.487737
A56: 2000-0216-GUF | B56: Hydrological | C56: Landslide (wet) | D56: 2000 | F56: French Guiana | H56: No | I56: No | J56: No | K56: 5 | M56: 53.487737
A57: 2000-0232-USA | B57: Hydrological | C57: Flash flood | D57: 2000 | F57: United States of America | H57: No | I57: No | J57: No | K57: 2000 | M57: 53.487737
A58: 2000-0275-URY | B58: Hydrological | C58: Flood (General) | D58: 2000 | F58: Uruguay | H58: No | I58: No | J58: No | K58: 5000 | M58: 53.487737
A59: 2000-0279-USA | B59: Climatological | C59: Forest fire | D59: 2000 | F59: United States of America | H59: No | I59: No | J59: No | M59: 53.487737
A60: 2000-0296-USA | B60: Hydrological | C60: Flood (General) | D60: 2000 | F60: United States of America | H60: No | I60: No | J60: No | K60: 240 | M60: 53.487737
A61: 2000-0310-CHL | B61: Hydrological | C61: Riverine flood | D61: 2000 | F61: Chile | H61: No | I61: No | J61: No | K61: 42000 | M61: 53.487737
A62: 2000-0360-USA | B62: Meteorological | C62: Severe weather | D62: 2000 | F62: United States of America | H62: No | I62: No | J62: No | M62: 53.487737
A63: 2000-0422-URY | B63: Meteorological | C63: Cold wave | D63: 2000 | F63: Uruguay | H63: No | I63: No | J63: No | K63: 400 | M63: 53.487737
A64: 2000-0375-CHL | B64: Hydrological | C64: Flash flood | D64: 2000 | E64: 30000 | F64: Chile | G64: Rain | H64: Yes | I64: No | J64: No | K64: 139667 | L64: 56088 | M64: 53.487737
A65: 2000-0416-BOL | B65: Meteorological | C65: Cold wave | D65: 2000 | F65: Bolivia (Plurinational State of) | H65: No | I65: No | J65: No | K65: 25277 | M65: 53.487737
A66: 2000-0420-CAN | B66: Meteorological | C66: Tornado | D66: 2000 | E66: 13000 | F66: Canada | H66: No | I66: No | J66: No | K66: 840 | L66: 24305 | M66: 53.487737
A67: 2000-0463-USA | B67: Meteorological | C67: Tornado | D67: 2000 | E67: 8100 | F67: United States of America | H67: No | I67: No | J67: No | K67: 1035 | L67: 15144 | M67: 53.487737
A68: 2000-0500-USA | B68: Hydrological | C68: Riverine flood | D68: 2000 | E68: 166000 | F68: United States of America | G68: Slide (land, mud, snow, rock) | H68: No | I68: No | J68: No | K68: 175 | L68: 310352 | M68: 53.487737
A69: 2000-0590-BRA | B69: Hydrological | C69: Riverine flood | D69: 2000 | F69: Brazil | H69: No | I69: No | J69: No | K69: 10000 | M69: 53.487737
A70: 2000-0598-USA | B70: Geophysical | C70: Ground movement | D70: 2000 | E70: 50000 | F70: United States of America | H70: No | I70: No | J70: No | K70: 25174 | L70: 93479 | M70: 53.487737
A71: 2000-0611-MEX | B71: Meteorological | C71: Severe weather | D71: 2000 | F71: Mexico | H71: No | I71: No | J71: No | K71: 300 | M71: 53.487737
A72: 2000-0614-USA | B72: Meteorological | C72: Tornado | D72: 2000 | E72: 90000 | F72: United States of America | H72: No | I72: No | J72: No | K72: 115 | L72: 168263 | M72: 53.487737
A73: 2000-0756-USA | B73: Meteorological | C73: Blizzard/Winter storm | D73: 2000 | F73: United States of America | H73: No | I73: No | J73: No | M73: 53.487737
A74: 2000-0797-HTI | B74: Hydrological | C74: Flood (General) | D74: 2000 | F74: Haiti | H74: No | I74: No | J74: No | K74: 1200 | M74: 53.487737
A75: 2000-0882-SLV | B75: Biological | C75: Viral disease | D75: 2000 | F75: El Salvador | H75: Yes | I75: No | J75: No | K75: 211 | M75: 53.487737
A76: 2000-9138-JAM | B76: Climatological | C76: Drought | D76: 2000 | E76: 6000 | F76: Jamaica | H76: No | I76: No | J76: No | L76: 11218 | M76: 53.487737
A77: 2000-9860-HND | B77: Climatological | C77: Drought | D77: 2000 | F77: Honduras | G77: Famine | H77: No | I77: No | J77: No | K77: 1125 | M77: 53.487737
A78: 2000-0080-USA | B78: Hydrological | C78: Riverine flood | D78: 2000 | F78: United States of America | G78: Slide (land, mud, snow, rock) | H78: No | I78: No | J78: No | K78: 231 | M78: 53.487737
A79: 2000-0081-COL | B79: Geophysical | C79: Ground movement | D79: 2000 | F79: Colombia | H79: No | I79: No | J79: No | K79: 430 | M79: 53.487737
A80: 2000-0175-USA | B80: Meteorological | C80: Tornado | D80: 2000 | E80: 450000 | F80: United States of America | H80: No | I80: No | J80: No | K80: 3300 | L80: 841314 | M80: 53.487737
A81: 2000-0215-HND | B81: Climatological | C81: Forest fire | D81: 2000 | F81: Honduras | H81: No | I81: No | J81: No | M81: 53.487737
A82: 2000-0240-USA | B82: Climatological | C82: Forest fire | D82: 2000 | E82: 1500000 | F82: United States of America | H82: No | I82: No | J82: No | K82: 25400 | L82: 2804381 | M82: 53.487737
A83: 2000-0255-ARG | B83: Hydrological | C83: Flood (General) | D83: 2000 | F83: Argentina | H83: No | I83: No | J83: No | K83: 30040 | M83: 53.487737
A84: 2000-0276-MEX | B84: Hydrological | C84: Flash flood | D84: 2000 | F84: Mexico | H84: No | I84: No | J84: No | M84: 53.487737
A85: 2000-0297-USA | B85: Hydrological | C85: Flood (General) | D85: 2000 | E85: 100000 | F85: United States of America | H85: No | I85: No | J85: No | K85: 300 | L85: 186959 | M85: 53.487737
A86: 2000-0299-GTM | B86: Hydrological | C86: Riverine flood | D86: 2000 | F86: Guatemala | H86: No | I86: No | J86: Yes | K86: 2524 | M86: 53.487737
A87: 2000-0403-PER | B87: Biological | C87: Locust infestation | D87: 2000 | F87: Peru | H87: No | I87: No | J87: No | M87: 53.487737
A88: 2000-0486-PRY | B88: Meteorological | C88: Cold wave | D88: 2000 | F88: Paraguay | H88: No | I88: No | J88: No | M88: 53.487737
A89: 2000-0609-GTM | B89: Hydrological | C89: Riverine flood | D89: 2000 | F89: Guatemala | G89: Slide (land, mud, snow, rock) | H89: No | I89: No | J89: No | K89: 462 | M89: 53.487737
A90: 2000-0650-VEN | B90: Hydrological | C90: Flood (General) | D90: 2000 | F90: Venezuela (Bolivarian Republic of) | H90: No | I90: No | J90: No | K90: 20004 | M90: 53.487737
A91: 2000-0627-PAN | B91: Hydrological | C91: Flood (General) | D91: 2000 | E91: 1300 | F91: Panama | H91: No | I91: No | J91: No | K91: 1000 | L91: 2430 | M91: 53.487737
A92: 2000-0644-NIC | B92: Meteorological | C92: Tropical cyclone | D92: 2000 | E92: 1000 | F92: Nicaragua | H92: No | I92: No | J92: No | K92: 2300 | L92: 1870 | M92: 53.487737
A93: 2000-0648-COL | B93: Hydrological | C93: Riverine flood | D93: 2000 | F93: Colombia | H93: No | I93: No | J93: No | K93: 28000 | M93: 53.487737
A94: 2000-0666-BRA | B94: Hydrological | C94: Riverine flood | D94: 2000 | F94: Brazil | H94: No | I94: No | J94: No | K94: 5000 | M94: 53.487737
A95: 2000-0733-ARG | B95: Hydrological | C95: Flood (General) | D95: 2000 | E95: 300000 | F95: Argentina | H95: No | I95: No | J95: No | L95: 560876 | M95: 53.487737
A96: 2000-0809-BRA | B96: Hydrological | C96: Riverine flood | D96: 2000 | F96: Brazil | G96: Slide (land, mud, snow, rock) | H96: No | I96: No | J96: No | K96: 2000 | M96: 53.487737
A97: 2000-0840-URY | B97: Meteorological | C97: Storm (General) | D97: 2000 | F97: Uruguay | H97: No | I97: No | J97: No | K97: 100 | M97: 53.487737
A98: 2000-0869-CUB | B98: Hydrological | C98: Flood (General) | D98: 2000 | F98: Cuba | H98: No | I98: No | J98: No | K98: 675 | M98: 53.487737
A99: 2000-9881-BOL | B99: Climatological | C99: Drought | D99: 2000 | F99: Bolivia (Plurinational State of) | H99: Yes | I99: No | J99: No | K99: 20000 | M99: 53.487737
A100: 2001-0553-BLZ | B100: Meteorological | C100: Tropical cyclone | D100: 2001 | E100: 250000 | F100: Belize | H100: No | I100: No | J100: No | K100: 20000 | L100: 454551 | M100: 54.999385
...

Sheet GDP
A1: Year | B1: GDP (current US$) | C1: Normalized Damage (xt) | D1: Keep
A2: 2000 | B2: 6.5544819e+11 | C2: 0 | D2: =IF(C2>=0.00001,"Yes","No") -> No
A3: 2001 | B3: 5.599837e+11 | C3: =('EM-DAT Data'!E314*1000)/GDP!B3 -> 8.0359481e-05 | D3: =IF(C3>=0.00001,"Yes","No") -> Yes
A4: 2002 | B4: 5.0979527e+11 | C4: 0 | D4: =IF(C4>=0.00001,"Yes","No") -> No
A5: 2003 | B5: 5.5823372e+11 | C5: =('EM-DAT Data'!E459*1000)/GDP!B5 -> 0.0005427834 | D5: =IF(C5>=0.00001,"Yes","No") -> Yes
A6: 2004 | B6: 6.6928932e+11 | C6: =('EM-DAT Data'!E707*1000)/GDP!B6 -> 5.528252e-07 | D6: =IF(C6>=0.00001,"Yes","No") -> No
A7: 2005 | B7: 8.9163383e+11 | C7: 0 | D7: =IF(C7>=0.00001,"Yes","No") -> No
A8: 2006 | B8: 1.1076267e+12 | C8: 0 | D8: =IF(C8>=0.00001,"Yes","No") -> No
A9: 2007 | B9: 1.3971142e+12 | C9: =('EM-DAT Data'!E788*1000)/GDP!B9 -> 8.9470135e-05 | D9: =IF(C9>=0.00001,"Yes","No") -> Yes
A10: 2008 | B10: 1.6958554e+12 | C10: =('EM-DAT Data'!E887*1000)/GDP!B10 -> 0.00065453694 | D10: =IF(C10>=0.00001,"Yes","No") -> Yes
A11: 2009 | B11: 1.6669963e+12 | C11: =('EM-DAT Data'!E984*1000)/GDP!B11 -> 0.00035992881 | D11: =IF(C11>=0.00001,"Yes","No") -> Yes
A12: 2010 | B12: 2.2088381e+12 | C12: =('EM-DAT Data'!E1055*1000)/GDP!B12 -> 0.00036308682 | D12: =IF(C12>=0.00001,"Yes","No") -> Yes
A13: 2011 | B13: 2.6161566e+12 | C13: =('EM-DAT Data'!E1171*1000)/GDP!B13 -> 0.00038300459 | D13: =IF(C13>=0.00001,"Yes","No") -> Yes
A14: 2012 | B14: 2.4652283e+12 | C14: =('EM-DAT Data'!E1254*1000)/GDP!B14 -> 6.9364773e-05 | D14: =IF(C14>=0.00001,"Yes","No") -> Yes
A15: 2013 | B15: 2.4728194e+12 | C15: =('EM-DAT Data'!E1356*1000)/GDP!B15 -> 0.0002205984 | D15: =IF(C15>=0.00001,"Yes","No") -> Yes
A16: 2014 | B16: 2.4560438e+12 | C16: =('EM-DAT Data'!E1462*1000)/GDP!B16 -> 8.1431774e-05 | D16: =IF(C16>=0.00001,"Yes","No") -> Yes
A17: 2015 | B17: 1.802212e+12 | C17: =('EM-DAT Data'!E1513*1000)/GDP!B17 -> 1.1097474e-06 | D17: =IF(C17>=0.00001,"Yes","No") -> No
A18: 2016 | B18: 1.7956933e+12 | C18: =('EM-DAT Data'!E1612*1000)/GDP!B18 -> 0.0001113776 | D18: =IF(C18>=0.00001,"Yes","No") -> Yes
A19: 2017 | B19: 2.0635147e+12 | C19: =('EM-DAT Data'!E1694*1000)/GDP!B19 -> 4.8461007e-05 | D19: =IF(C19>=0.00001,"Yes","No") -> Yes
A20: 2018 | B20: 1.9169337e+12 | C20: =('EM-DAT Data'!E1881*1000)/GDP!B20 -> 2.7648322e-05 | D20: =IF(C20>=0.00001,"Yes","No") -> Yes
A21: 2019 | B21: 1.8732882e+12 | C21: 0 | D21: =IF(C21>=0.00001,"Yes","No") -> No
A22: 2020 | B22: 1.4761073e+12 | C22: =('EM-DAT Data'!E1963*1000)/GDP!B22 -> 0.00033872876 | D22: =IF(C22>=0.00001,"Yes","No") -> Yes
A23: 2021 | B23: 1.6706475e+12 | C23: =('EM-DAT Data'!E2090*1000)/GDP!B23 -> 0.00032502369 | D23: =IF(C23>=0.00001,"Yes","No") -> Yes
A24: 2022 | B24: 1.9519238e+12 | C24: =('EM-DAT Data'!E2188*1000)/GDP!B24 -> 0.0005845515 | D24: =IF(C24>=0.00001,"Yes","No") -> Yes
A25: 2023 | B25: 2.1911319e+12 | C25: =('EM-DAT Data'!E2328*1000)/GDP!B25 -> 0.00018766556 | D25: =IF(C25>=0.00001,"Yes","No") -> Yes
A26: 2024 | B26: 2.1858216e+12 | C26: =('EM-DAT Data'!E2402*1000)/GDP!B26 -> 0.0034586536 | D26: =IF(C26>=0.00001,"Yes","No") -> Yes

Sheet GDP-keep
A1: =GDP!A1 -> Year | B1: =GDP!B1 -> GDP (current US$) | C1: Normalized Damage (xt) | D1: =GDP!D1 -> Keep
A2: =GDP!A2 -> 2000 | B2: =GDP!B2 -> 6.5544819e+11 | C2: =GDP!C2 -> 0 | D2: =GDP!D2 -> No
A3: =GDP!A3 -> 2001 | B3: =GDP!B3 -> 5.599837e+11 | C3: =GDP!C3 -> 8.0359481e-05 | D3: =GDP!D3 -> Yes
A4: =GDP!A4 -> 2002 | B4: =GDP!B4 -> 5.0979527e+11 | C4: =GDP!C4 -> 0 | D4: =GDP!D4 -> No
A5: =GDP!A5 -> 2003 | B5: =GDP!B5 -> 5.5823372e+11 | C5: =GDP!C5 -> 0.0005427834 | D5: =GDP!D5 -> Yes
A6: =GDP!A6 -> 2004 | B6: =GDP!B6 -> 6.6928932e+11 | C6: =GDP!C6 -> 5.528252e-07 | D6: =GDP!D6 -> No
A7: =GDP!A7 -> 2005 | B7: =GDP!B7 -> 8.9163383e+11 | C7: =GDP!C7 -> 0 | D7: =GDP!D7 -> No
A8: =GDP!A8 -> 2006 | B8: =GDP!B8 -> 1.1076267e+12 | C8: =GDP!C8 -> 0 | D8: =GDP!D8 -> No
A9: =GDP!A9 -> 2007 | B9: =GDP!B9 -> 1.3971142e+12 | C9: =GDP!C9 -> 8.9470135e-05 | D9: =GDP!D9 -> Yes
A10: =GDP!A10 -> 2008 | B10: =GDP!B10 -> 1.6958554e+12 | C10: =GDP!C10 -> 0.00065453694 | D10: =GDP!D10 -> Yes
A11: =GDP!A11 -> 2009 | B11: =GDP!B11 -> 1.6669963e+12 | C11: =GDP!C11 -> 0.00035992881 | D11: =GDP!D11 -> Yes
A12: =GDP!A12 -> 2010 | B12: =GDP!B12 -> 2.2088381e+12 | C12: =GDP!C12 -> 0.00036308682 | D12: =GDP!D12 -> Yes
A13: =GDP!A13 -> 2011 | B13: =GDP!B13 -> 2.6161566e+12 | C13: =GDP!C13 -> 0.00038300459 | D13: =GDP!D13 -> Yes
... A26: =GDP!A26 -> 2024 | B26: =GDP!B26 -> 2.1858216e+12 | C26: =GDP!C26 -> 0.0034586536 | D26: =GDP!D26 -> Yes

Sheet EM-DAT Info
A1: Source: | B1: EM-DAT, CRED / UCLouvain, Brussels, Belgium
B2: https://www.emdat.be
A3: Glossary: | B3: https://doc.emdat.be/docs/data-structure-and-content/emdat-public-table/
A4: Version: | B4: 2026-05-08
A5: File creation: | B5: Sat, 16 May 2026 17:15:52 UTC
A6: Table type: | B6: public_emdat_custom_request
A7: # of records: | B7: 2474

Sheet table 1
A1: Observation | B1: Year | C1: Normalised damage ratio (xt) | D1: Damage as % of annual GDP | E1: Retained
A2: 1 | B2: 2001 | C2: 8.03595e-05 | D2: 8e-05 | E2: Yes
A3: 2 | B3: 2003 | C3: 0.0005427834 | D3: 0.000543 | E3: Yes
A4: 3 | B4: 2007 | C4: 8.94701e-05 | D4: 8.9e-05 | E4: Yes
A5: 4 | B5: 2008 | C5: 0.0006545369 | D5: 0.000655 | E5: Yes
A6: 5 | B6: 2009 | C6: 0.0003599288 | D6: 0.00036 | E6: Yes
A7: 6 | B7: 2010 | C7: 0.0003630868 | D7: 0.000363 | E7: Yes
A8: 7 | B8: 2011 | C8: 0.0003830046 | D8: 0.000383 | E8: Yes
A9: 8 | B9: 2012 | C9: 6.93648e-05 | D9: 6.9e-05 | E9: Yes
A10: 9 | B10: 2013 | C10: 0.0002205984 | D10: 0.000221 | E10: Yes
A11: 10 | B11: 2014 | C11: 8.14318e-05 | D11: 8.1e-05 | E11: Yes
A12: 11 | B12: 2016 | C12: 0.0001113776 | D12: 0.000111 | E12: Yes
A13: 12 | B13: 2017 | C13: 4.8461e-05 | D13: 4.8e-05 | E13: Yes
... A19: 18 | B19: 2024 | C19: 0.0034586536 | D19: 0.003459 | E19: Yes
